<?xml version='1.0' encoding='UTF-8'?>
<song xmlns="http://openlyrics.info/namespace/2009/song" version="0.8" createdIn="OpenLP 2.4.6" modifiedIn="OpenLP 2.4.6" modifiedDate="2019-12-27T02:57:46">
  <properties>
    <titles>
      <title>C176 - caTTaan-ko maha-bhandaa miTho</title>
    </titles>
    <authors>
      <author>Unknown</author>
    </authors>
  </properties>
  <format>
    <tags application="OpenLP">
      <tag name="y">
        <open>&lt;span style="-webkit-text-fill-color:yellow"&gt;</open>
        <close>&lt;/span&gt;</close>
      </tag>
    </tags>
  </format>
  <lyrics>
    <verse name="v1">
      <lines>(चट्टानको महभन्दा मीठो) २<br/>प्रभु चट्टानको महभन्दा मीठो छल्<br/>चाखीहेर, प्रभु भलो छन्<br/>प्रभु चट्टानको महभन्दा मीठो छन्<br/><br/><tag name="y">(caTTaan-ko maha-bhandaa miTho) ~2<br/>prabhu caTTaan-ko<br/>maha-bhandaa miTho chan,<br/>caakhi heraa, prabhu bhalo chan<br/>prabhu caTTaan-ko<br/>maha-bhandaa miTho chan.<br/></tag></lines>
    </verse>
  </lyrics>
</song>
